examples/__init__.py
examples/async_stream_chat.py
examples/async_stream_complete.py
examples/cpu_offline_inference.py
examples/offline_inference.py
examples/openai_chat_client.py
examples/openai_complete_client.py
examples/speculative_decoding.py
examples/stream_chat.py
examples/stream_complete.py
scalellm/_C.cpython-310-x86_64-linux-gnu.so
scalellm/__init__.py
scalellm/downloader.py
scalellm/errors.py
scalellm/llm.py
scalellm/llm_engine.py
scalellm/version.py
scalellm/_C/__init__.pyi
scalellm/_C/llm_handler.pyi
scalellm/_C/output.pyi
scalellm/_C/sampling_params.pyi
scalellm/serve/__init__.py
scalellm/serve/api_protocol.py
scalellm/serve/api_server.py
scalellm/serve/chat_handler.py
scalellm/serve/common.py
scalellm/serve/completion_handler.py
scalellm/serve/server_args.py
scalellm/serve/streaming_response.py
scalellm-0.2.6.dist-info/licenses/LICENSE
scalellm-0.2.6.dist-info/METADATA
scalellm-0.2.6.dist-info/WHEEL
scalellm-0.2.6.dist-info/top_level.txt
scalellm-0.2.6.dist-info/RECORD
