Metadata-Version: 2.4
Name: scalellm
Version: 0.2.6
Summary: A high-performance inference system for large language models.
Home-page: https://github.com/vectorch-ai/ScaleLLM
Author: ScaleLLM Team
Author-email: mi@vectorch.com
License: Apache 2.0
Classifier: Development Status :: 3 - Alpha
Classifier: Intended Audience :: Developers
Classifier: Intended Audience :: Education
Classifier: Programming Language :: C++
Classifier: Programming Language :: Python :: 3 :: Only
Classifier: Programming Language :: Python :: 3.8
Classifier: Programming Language :: Python :: 3.9
Classifier: Programming Language :: Python :: 3.10
Classifier: Programming Language :: Python :: 3.11
Classifier: Programming Language :: Python :: 3.12
Classifier: Environment :: GPU :: NVIDIA CUDA
Classifier: Operating System :: POSIX
Classifier: License :: OSI Approved :: Apache Software License
Classifier: Topic :: Scientific/Engineering
Classifier: Topic :: Scientific/Engineering :: Artificial Intelligence
Requires-Python: >=3.8
License-File: LICENSE
Requires-Dist: torch>=2.1.0
Requires-Dist: fastapi>=0.110.0
Requires-Dist: huggingface_hub
Requires-Dist: shortuuid
Requires-Dist: safetensors
Requires-Dist: numpy
Requires-Dist: uvicorn
Dynamic: author
Dynamic: author-email
Dynamic: classifier
Dynamic: description
Dynamic: description-content-type
Dynamic: home-page
Dynamic: license
Dynamic: license-file
Dynamic: requires-dist
Dynamic: requires-python
Dynamic: summary
